bin_collection/__init__.py
bin_collection/bin_collection.py
bin_collection/test_samples.py
bin_collection-0.1.dist-info/DESCRIPTION.rst
bin_collection-0.1.dist-info/METADATA
bin_collection-0.1.dist-info/RECORD
bin_collection-0.1.dist-info/WHEEL
bin_collection-0.1.dist-info/metadata.json
bin_collection-0.1.dist-info/top_level.txt
