Metadata-Version: 2.0
Name: bin-collection
Version: 0.1
Summary: A lib for checking bin collections from icalendar data
Home-page: https://github.com/Gmiller290488/bin_collection
Author: Gareth Miller
Author-email: gmiller290488@gmail.com
License: UNKNOWN
Download-URL: https://github.com/peterldowns/Gmiller290488/bin_collection/0.1.tar.gz
Keywords: techtest,ical
Platform: UNKNOWN
Requires-Dist: icalendar
Requires-Dist: markdown
Requires-Dist: request
